{"lbars":{"username":"lbars","password":"Landon","email":"lbars@hawaii.edu","fullname":"Landon Barsatan"},"test":{"username":"test","password":"123456","email":"test@hotmail.com","fullname":"Test t"},"test1":{"username":"test1","password":"654321","email":"test1@gmail.com","fullname":"Testing test"},"test3":{"username":"test3","password":"123321","email":"test3@gmail.com","fullname":"Landon Barsatan"},"test2":{"username":"test2","password":"test123","email":"test2@hawaii.edu","fullname":"John Doe"},"itm352":{"username":"itm352","password":"grader","email":"student@hawaii.edu","fullname":"Student Test"},"test4":{"username":"test4","password":"987654","email":"test4@gmail.com","fullname":"tester t"},"test5":{"username":"test5","password":"test111","email":"test5@gmail.com","fullname":"Testing test"},"test6":{"username":"test6","password":"test61234","email":"test6@gmail.com","fullname":"test again"},"test7":{"username":"test7","password":"test9876","email":"test7@gmail.com","fullname":"test again"},"test8":{"username":"test8","password":"test1234","email":"test8@gmail.com","fullname":"Jane Doe"},"test9":{"username":"test9","password":"password","email":"test9@gmail.com","fullname":"Jane Doe"},"test10":{"username":"test10","password":"password","email":"test10@gmail.com","fullname":"tester test"},"test11":{"username":"test11","password":"dfsdfsdfsfs","email":"test11@gmail.com","fullname":"Lol haha"},"testpass":{"username":"testpass","password":"123456","email":"testpass@gmail.com","fullname":"test password"},"testpass2":{"username":"testpass2","password":"123456","email":"testpass2@gmail.com","fullname":"Test Passwordtwo"},"hihello":{"username":"hihello","password":"123456","email":"hihello@gmail.com","fullname":"Hi hello"}}